fixseqpadding/__init__.py
fixseqpadding/__main__.py
fixSeqPadding-2.0.0.dist-info/LICENSE
fixSeqPadding-2.0.0.dist-info/METADATA
fixSeqPadding-2.0.0.dist-info/WHEEL
fixSeqPadding-2.0.0.dist-info/entry_points.txt
fixSeqPadding-2.0.0.dist-info/top_level.txt
fixSeqPadding-2.0.0.dist-info/RECORD
